pelican_myst/__about__.py
pelican_myst/__init__.py
pelican_myst-0.1.0.dist-info/LICENSE
pelican_myst-0.1.0.dist-info/WHEEL
pelican_myst-0.1.0.dist-info/METADATA
pelican_myst-0.1.0.dist-info/RECORD
